alira_licensing/__init__.py
alira_licensing/license.py
levatas_alira_licensing-2.0.3.dist-info/METADATA
levatas_alira_licensing-2.0.3.dist-info/WHEEL
levatas_alira_licensing-2.0.3.dist-info/top_level.txt
levatas_alira_licensing-2.0.3.dist-info/RECORD
