Metadata-Version: 2.1
Name: levatas-alira-licensing
Version: 2.0.3
Summary: Alira Licensing
Home-page: https://github.com/vinsa-ai/alira-licensing
Author: Levatas
Author-email: svpino@gmail.com
License: UNKNOWN
Platform: UNKNOWN
Requires-Dist: cryptography
